mcafeesecure_csv/__init__.py
mcafeesecure_csv/mcafeesecure_csv.py
mcafeesecure_csv-0.0.2.dist-info/LICENSE
mcafeesecure_csv-0.0.2.dist-info/METADATA
mcafeesecure_csv-0.0.2.dist-info/WHEEL
mcafeesecure_csv-0.0.2.dist-info/top_level.txt
mcafeesecure_csv-0.0.2.dist-info/RECORD
