Metadata-Version: 2.1
Name: mcafeesecure-csv
Version: 0.0.2
Summary: CSV Report Generator for McAfee SECURE
Home-page: https://github.com/zacharyts/
Author: Zachary Collins
Author-email: zachary@mcafeesecure.com
License: UNKNOWN
Platform: UNKNOWN
Classifier: Programming Language :: Python :: 3
Classifier: License :: OSI Approved :: MIT License
Classifier: Operating System :: OS Independent
Requires-Dist: mcafeesecure-api
Requires-Dist: pandas
